{
    "code": 200,
    "message": "查询成功",
    "data": {
        "items": [
            {
                "id": "02bf7d95-f490-4a4d-a77a-7c8fb0151cbd",
                "deviceId": "SYS-INV-1-001",
                "deviceName": "1#日用逆变器系统",
                "deviceType": "逆变器系统",
                "model": "AC-INV-190A",
                "manufacturer": "某逆变器制造商",
                "location": "配电室",
                "status": "normal",
                "commissionDate": "2024-01-25",
                "description": "1号日用逆变器及配套设备，额定输出电流190A",
                "createdAt": "2025-12-11T17:08:04.000Z",
                "updatedAt": "2025-12-19T15:14:27.000Z"
            },
            {
                "id": "10bf2d36-3148-4496-977b-c1a4a3a97eed",
                "deviceId": "SYS-COOL-001",
                "deviceName": "冷却水泵系统",
                "deviceType": "辅助系统",
                "model": "CP-Dual-100L",
                "manufacturer": "某泵制造商",
                "location": "机舱",
                "status": "normal",
                "commissionDate": "2024-02-05",
                "description": "冷却水循环泵及管路系统，包含2台泵，额定流量100L/min，额定压力0.1MPa",
                "createdAt": "2025-12-11T17:08:04.000Z",
                "updatedAt": "2025-12-18T17:05:03.000Z"
            },
            {
                "id": "2a3aa4be-b43c-4518-ab77-c21fc2861c19",
                "deviceId": "SYS-BILGE-001",
                "deviceName": "舱底水系统",
                "deviceType": "辅助系统",
                "model": "BW-Monitor-4Wells",
                "manufacturer": "某传感器制造商",
                "location": "舱底各区",
                "status": "normal",
                "commissionDate": "2024-01-10",
                "description": "舱底水集水井及排水系统，包含4个集水井水位监测",
                "createdAt": "2025-12-11T17:08:04.000Z",
                "updatedAt": "2025-12-18T17:05:16.000Z"
            },
            {
                "id": "a6713a6d-eb68-469c-9370-bd2b67295472",
                "deviceId": "SYS-INV-2-001",
                "deviceName": "2#日用逆变器系统",
                "deviceType": "逆变器系统",
                "model": "AC-INV-190A",
                "manufacturer": "某逆变器制造商",
                "location": "配电室",
                "status": "normal",
                "commissionDate": "2024-01-25",
                "description": "2号日用逆变器及配套设备，额定输出电流190A",
                "createdAt": "2025-12-11T17:08:04.000Z",
                "updatedAt": "2025-12-11T17:08:04.000Z"
            },
            {
                "id": "d48b576c-8a90-4492-b9a0-f1479ec8f41c",
                "deviceId": "SYS-DCPD-001",
                "deviceName": "直流配电板系统",
                "deviceType": "配电系统",
                "model": "DCB-750V-1000A",
                "manufacturer": "某配电设备制造商",
                "location": "主配电室",
                "status": "normal",
                "commissionDate": "2024-01-20",
                "description": "直流母排配电及保护系统，额定电压750V，额定电流1000A",
                "createdAt": "2025-12-11T17:08:04.000Z",
                "updatedAt": "2025-12-11T17:08:04.000Z"
            },
            {
                "id": "7d6849fb-5704-4ca0-8237-b974b27cbf49",
                "deviceId": "SYS-BAT-001",
                "deviceName": "电池系统",
                "deviceType": "电池装置",
                "model": "LFP-648V-300Ah",
                "manufacturer": "某电池制造商",
                "location": "电池舱",
                "status": "normal",
                "commissionDate": "2024-01-15",
                "description": "锂电池能源管理系统，包含BMS及所有电池单元，额定电压648V，总容量300Ah",
                "createdAt": "2025-12-11T17:08:03.000Z",
                "updatedAt": "2025-12-11T17:08:03.000Z"
            },
            {
                "id": "bb905811-1a70-417a-8602-8e10959f7c22",
                "deviceId": "SYS-PROP-L-001",
                "deviceName": "左推进系统",
                "deviceType": "推进系统",
                "model": "PROP-L-1500kW",
                "manufacturer": "某推进系统制造商",
                "location": "机舱左侧",
                "status": "normal",
                "commissionDate": "2024-02-01",
                "description": "左侧推进电机及其逆变控制系统，永磁同步电机，额定功率1500kW",
                "createdAt": "2025-12-11T17:08:03.000Z",
                "updatedAt": "2025-12-11T17:08:03.000Z"
            },
            {
                "id": "f8526635-1610-42e5-88ff-5f79620821ad",
                "deviceId": "SYS-PROP-R-001",
                "deviceName": "右推进系统",
                "deviceType": "推进系统",
                "model": "PROP-R-1500kW",
                "manufacturer": "某推进系统制造商",
                "location": "机舱右侧",
                "status": "normal",
                "commissionDate": "2024-02-01",
                "description": "右侧推进电机及其逆变控制系统，永磁同步电机，额定功率1500kW",
                "createdAt": "2025-12-11T17:08:03.000Z",
                "updatedAt": "2025-12-11T17:08:03.000Z"
            }
        ],
        "total": 8,
        "page": "1",
        "pageSize": "100",
        "totalPages": 1
    },
    "timestamp": 1766376600111
}